tardis/__init__.py
tardis/clients/__init__.py
tardis/clients/csv_client.py
tardis/database/client.py
tardis/database/table.py
tardis/database/utils.py
tardis/ingestors/base_ingestor.py
tardis/ingestors/candle_ingestor.py
tardis/ingestors/derived_option_chain_ingestor.py
tardis/ingestors/option_chain_ingestor.py
tardis/ingestors/perpetuals_ingestor.py
tardis/managers/downloands_manager.py
tardis/models/__init__.py
tardis/models/exchange/__init__.py
tardis/models/exchange/api_key_info.py
tardis/models/exchange/data_type.py
tardis/models/exchange/exchange.py
tardis/models/exchange/exchange_details.py
tardis/models/exchange/grouped_symbols.py
tardis/models/exchange/symbol_type.py
tardis/models/outputs/__init__.py
tardis/models/outputs/data_types.py
tardis/models/outputs/table_schemas.py
tardis/syncs/__init__.py
tardis/syncs/candles.py
tardis/syncs/chain.py
tardis/syncs/derived_chain.py
tardis/syncs/perpetuals.py
tardis/utils.py
tardis_ingestors-0.4.5.dist-info/WHEEL
tardis_ingestors-0.4.5.dist-info/METADATA
tardis_ingestors-0.4.5.dist-info/RECORD
