Metadata-Version: 2.1
Name: tardis-ingestors
Version: 0.4.5
Summary: Tardis.dev ingestors for processed data
License: MIT
Author: miguel-bm
Author-email: miguel.blanco.marcos@gmail.com
Requires-Python: >=3.7.1,<4.0.0
Classifier: License :: OSI Approved :: MIT License
Classifier: Programming Language :: Python :: 3
Classifier: Programming Language :: Python :: 3.10
Classifier: Programming Language :: Python :: 3.8
Classifier: Programming Language :: Python :: 3.9
Requires-Dist: SQLAlchemy (>=1.4.36,<2.0.0)
Requires-Dist: dask[dataframe] (==2020.12.0)
Requires-Dist: pandas (==1.3.4)
Requires-Dist: pg8000 (>=1.26.1,<2.0.0)
Requires-Dist: py_vollib (>=1.0.1,<2.0.0)
Requires-Dist: pydantic (>=1.9.0,<2.0.0)
Requires-Dist: python-dotenv (>=0.20.0,<0.21.0)
Requires-Dist: requests (>=2.27.1,<3.0.0)
Requires-Dist: tardis-dev (>=2.0.0-alpha.10,<3.0.0)
Requires-Dist: typedframe (>=0.6.2,<0.7.0)
